setup.py
dynofunc/__init__.py
dynofunc/attribute.py
dynofunc/db.py
dynofunc/table.py
dynofunc.egg-info/PKG-INFO
dynofunc.egg-info/SOURCES.txt
dynofunc.egg-info/dependency_links.txt
dynofunc.egg-info/requires.txt
dynofunc.egg-info/top_level.txt
dynofunc/core/Immutable.py
dynofunc/core/args.py
dynofunc/core/builder.py
dynofunc/core/dynamo.py
dynofunc/core/exceptions.py
dynofunc/core/executor.py
dynofunc/core/model.py
dynofunc/core/response.py
dynofunc/core/utils.py
dynofunc/operations/add.py
dynofunc/operations/create.py
dynofunc/operations/delete.py
dynofunc/operations/describe.py
dynofunc/operations/find.py
dynofunc/operations/query.py
dynofunc/operations/scan.py
dynofunc/operations/update.py