Metadata-Version: 1.2
Name: dynofunc
Version: 1.0.0
Summary: A small interface for more easily making calls to dynamo using boto.
Home-page: https://github.com/rayepps/dynofunc
Author: Ray Epps
Author-email: rayharryepps@gmail.com
License: UNKNOWN
Platform: UNKNOWN
Classifier: Development Status :: 3 - Alpha
Classifier: Intended Audience :: Developers
Classifier: Topic :: Software Development :: Libraries
Classifier: License :: OSI Approved :: MIT License
Classifier: Programming Language :: Python :: 3
Classifier: Programming Language :: Python :: 3.4
Classifier: Programming Language :: Python :: 3.5
Classifier: Programming Language :: Python :: 3.6
Classifier: Operating System :: OS Independent
Requires-Python: >=3
